MANIFEST.in
README
setup.py
examples/bookmarks2rss.py
examples/rss2.mako
python_weave.egg-info/PKG-INFO
python_weave.egg-info/SOURCES.txt
python_weave.egg-info/dependency_links.txt
python_weave.egg-info/not-zip-safe
python_weave.egg-info/requires.txt
python_weave.egg-info/top_level.txt
weave/PBKDF2.py
weave/__init__.py
weave/client.py
weave/crypto.py
weave/exceptions.py
weave/storage.py
weave/user.py
weave/util.py
weave/server/__init__.py
weave/server/bottle.py
weave/server/decorators.py
weave/server/storage.py
weave/server/sync.py
weave/server/users.py
weave/tests/__init__.py
weave/tests/support.py
weave/tests/test_server_storage.py
weave/tests/test_storage.py