Metadata-Version: 1.0
Name: python-weave
Version: 0.2
Summary: A Mozilla Weave client for Python
Home-page: http://wiki.mozilla.org/Labs/Weave
Author: Mike Hanson
Author-email: mhanson@mozilla.com
License: UNKNOWN
Platform: UNKNOWN
Classifier: Development Status :: 2 - Pre-Alpha
Classifier: Intended Audience :: Developers
Classifier: License :: OSI Approved :: Mozilla Public License 1.1 (MPL 1.1)
Classifier: License :: OSI Approved :: GNU Library or Lesser General Public License (LGPL)
Classifier: Operating System :: OS Independent
Classifier: Programming Language :: Python
Classifier: Programming Language :: Python :: 3
Classifier: Topic :: Software Development :: Libraries :: Python Modules
